[
  {
    "type": "department",
    "department": "Civil Technology",
    "semester": "8th",
    "shift": "Morning",
    "senderId": "2222222",
    "text": "vbv",
    "images": [],
    "id": 1765870244747,
    "createdAt": "2025-12-16T07:30:44.747Z",
    "seenBy": [
      "2222222"
    ]
  },
  {
    "type": "department",
    "department": "Civil Technology",
    "semester": "8th",
    "shift": "Morning",
    "senderId": "2222222",
    "text": "",
    "images": [],
    "id": 1765870253249,
    "createdAt": "2025-12-16T07:30:53.249Z",
    "seenBy": [
      "2222222"
    ],
    "reactions": [
      {
        "userId": "2222222",
        "reaction": "😂"
      }
    ]
  },
  {
    "type": "department",
    "department": "Civil Technology",
    "semester": "8th",
    "shift": "Morning",
    "senderId": "2222222",
    "text": "5445",
    "images": [],
    "id": 1765876945523,
    "createdAt": "2025-12-16T09:22:25.523Z",
    "seenBy": [
      "2222222"
    ]
  },
  {
    "type": "department",
    "department": "Civil Technology",
    "semester": "8th",
    "shift": "Morning",
    "senderId": "2222222",
    "text": "",
    "images": [],
    "id": 1765876949961,
    "createdAt": "2025-12-16T09:22:29.961Z",
    "seenBy": [
      "2222222"
    ]
  },
  {
    "type": "department",
    "department": "Civil Technology",
    "semester": "8th",
    "shift": "Morning",
    "senderId": "2222222",
    "text": "",
    "images": [],
    "id": 1765877127271,
    "createdAt": "2025-12-16T09:25:27.271Z",
    "seenBy": [
      "2222222"
    ],
    "reactions": [
      {
        "userId": "2222222",
        "reaction": "😂"
      }
    ]
  },
  {
    "type": "department",
    "department": "Civil Technology",
    "semester": "2nd",
    "shift": "Morning",
    "senderId": "2222222",
    "text": "",
    "images": [
      "1765907246779-878029286.png"
    ],
    "id": 1765907246793,
    "createdAt": "2025-12-16T17:47:26.793Z",
    "seenBy": [
      "2222222"
    ]
  }
]